requests/__init__.py
requests/__version__.py
requestsaa-0.1.2.dist-info/LICENSE
requestsaa-0.1.2.dist-info/METADATA
requestsaa-0.1.2.dist-info/WHEEL
requestsaa-0.1.2.dist-info/top_level.txt
requestsaa-0.1.2.dist-info/RECORD
